mala.py
Mala-0.1.0.dist-info/DESCRIPTION.rst
Mala-0.1.0.dist-info/METADATA
Mala-0.1.0.dist-info/RECORD
Mala-0.1.0.dist-info/WHEEL
Mala-0.1.0.dist-info/metadata.json
Mala-0.1.0.dist-info/top_level.txt
