Metadata-Version: 2.0
Name: Mala
Version: 0.1.0
Summary: Get metadata from DHT network
Home-page: https://github.com/whtsky/mala
Author: whtsky
Author-email: whtsky@gmail.com
License: BSDv3
Keywords: dht,asyncio,bt,metainfo
Platform: any
Classifier: Environment :: Other Environment
Classifier: Intended Audience :: Developers
Classifier: License :: OSI Approved :: BSD License
Classifier: Operating System :: OS Independent
Classifier: Programming Language :: Python
Classifier: Programming Language :: Python :: 3.5
Classifier: Programming Language :: Python :: Implementation :: CPython
Requires-Dist: bencoder.pyx (>=1.1.1)
